[
  {
    "kind": "youtube#playlistItem",
    "etag": "CdqV_YNAXgGKtUMFIdSC9t6lctg",
    "id": "UExnRThCMVNkQ1REc2hYVzNFVDZVSFFRemF2NjVweF9ReC44QTA1QTQyRTc3M0VGQzYx",
    "snippet": {
      "publishedAt": "2024-09-09T17:38:49Z",
      "channelId": "UClYsncuu6rBhsh2lYYb0zdQ",
      "title": "Finding Hope in the Dark Times: How to Feed the Wolf of Hope",
      "description": "In today’s message, we explore the powerful role of hope in our lives, especially during tough times. Just like people search for miraculous treatments, we all look for hope to overcome our challenges. Whether you're struggling with illness, feeling down, or just trying to stay positive, hope is essential for our well-being.\n\nJoin us as we discuss:\n* How hope helps us face the future.\n* Personal stories of battling hopelessness.\n* Practical steps to feed hope into our lives, including sharing with others, turning to God’s word, practicing gratitude, and always looking forward.\n\nWe’ll discover how hope is like the oxygen for our spirit and how we can cultivate it even when it feels out of reach. Remember, you’re not alone—let’s find hope together!",
      "thumbnails": {
        "default": {
          "url": "https://i.ytimg.com/vi/IoMses1YAgc/default.jpg",
          "width": 120,
          "height": 90
        },
        "medium": {
          "url": "https://i.ytimg.com/vi/IoMses1YAgc/mqdefault.jpg",
          "width": 320,
          "height": 180
        },
        "high": {
          "url": "https://i.ytimg.com/vi/IoMses1YAgc/hqdefault.jpg",
          "width": 480,
          "height": 360
        },
        "standard": {
          "url": "https://i.ytimg.com/vi/IoMses1YAgc/sddefault.jpg",
          "width": 640,
          "height": 480
        },
        "maxres": {
          "url": "https://i.ytimg.com/vi/IoMses1YAgc/maxresdefault.jpg",
          "width": 1280,
          "height": 720
        }
      },
      "channelTitle": "The Woodlands Methodist Church",
      "playlistId": "PLgE8B1SdCTDshXW3ET6UHQQzav65px_Qx",
      "position": 0,
      "resourceId": {
        "kind": "youtube#video",
        "videoId": "IoMses1YAgc"
      },
      "videoOwnerChannelTitle": "The Woodlands Methodist Church",
      "videoOwnerChannelId": "UClYsncuu6rBhsh2lYYb0zdQ"
    },
    "playlistName": "Loft"
  },
  {
    "kind": "youtube#playlistItem",
    "etag": "Z14Jbvk-frzfbBDcshrultefNNU",
    "id": "UExnRThCMVNkQ1REc2hYVzNFVDZVSFFRemF2NjVweF9ReC4wMDFGNzBEOTU4Q0Y1Q0RG",
    "snippet": {
      "publishedAt": "2024-09-03T17:07:47Z",
      "channelId": "UClYsncuu6rBhsh2lYYb0zdQ",
      "title": "Overcoming Envy with Contentment: Feeding the Right Wolf",
      "description": "Are you tired of feeling like you need more to be happy? In this message, we explore how today's constant stream of ads and social media can feed our envy. But God’s Word offers us another way—the path of contentment. \n\nJoin us as we learn how to push back against envy and embrace the peace that comes from knowing that Jesus is enough. We’ll talk about real-life struggles, share stories and dive into what the Bible says about finding true satisfaction. \n\nThis message will help you focus on what really matters in life. Watch now to discover how to feed the good wolf of contentment in your life.",
      "thumbnails": {
        "default": {
          "url": "https://i.ytimg.com/vi/_hGIEp9W-WE/default.jpg",
          "width": 120,
          "height": 90
        },
        "medium": {
          "url": "https://i.ytimg.com/vi/_hGIEp9W-WE/mqdefault.jpg",
          "width": 320,
          "height": 180
        },
        "high": {
          "url": "https://i.ytimg.com/vi/_hGIEp9W-WE/hqdefault.jpg",
          "width": 480,
          "height": 360
        },
        "standard": {
          "url": "https://i.ytimg.com/vi/_hGIEp9W-WE/sddefault.jpg",
          "width": 640,
          "height": 480
        },
        "maxres": {
          "url": "https://i.ytimg.com/vi/_hGIEp9W-WE/maxresdefault.jpg",
          "width": 1280,
          "height": 720
        }
      },
      "channelTitle": "The Woodlands Methodist Church",
      "playlistId": "PLgE8B1SdCTDshXW3ET6UHQQzav65px_Qx",
      "position": 1,
      "resourceId": {
        "kind": "youtube#video",
        "videoId": "_hGIEp9W-WE"
      },
      "videoOwnerChannelTitle": "The Woodlands Methodist Church",
      "videoOwnerChannelId": "UClYsncuu6rBhsh2lYYb0zdQ"
    },
    "playlistName": "Loft"
  },
  {
    "kind": "youtube#playlistItem",
    "etag": "UwVGtBYLiMnmuK3leu1FbQF9YK4",
    "id": "UExnRThCMVNkQ1REc2hYVzNFVDZVSFFRemF2NjVweF9ReC4xNTZBNUQxMDZBQzFGMjkw",
    "snippet": {
      "publishedAt": "2024-08-28T14:13:45Z",
      "channelId": "UClYsncuu6rBhsh2lYYb0zdQ",
      "title": "Make It a Great Day or Not: The Choice Is Yours",
      "description": "In this week’s message, we explore the power of choice in shaping our days and our lives. Through personal stories and timeless wisdom, we learn that life is not about what happens to us, but how we react to it. Discover how to overcome the “victim mentality” and embrace the victorious life God has for us. \n\nDrawing from an ancient Cherokee proverb, the story of Job, and the message of the cross, we’re reminded that even in tough times, we can choose to be victors, not victims. Watch and be encouraged to keep getting back up, no matter what comes your way!",
      "thumbnails": {
        "default": {
          "url": "https://i.ytimg.com/vi/ayOKJoYnREI/default.jpg",
          "width": 120,
          "height": 90
        },
        "medium": {
          "url": "https://i.ytimg.com/vi/ayOKJoYnREI/mqdefault.jpg",
          "width": 320,
          "height": 180
        },
        "high": {
          "url": "https://i.ytimg.com/vi/ayOKJoYnREI/hqdefault.jpg",
          "width": 480,
          "height": 360
        },
        "standard": {
          "url": "https://i.ytimg.com/vi/ayOKJoYnREI/sddefault.jpg",
          "width": 640,
          "height": 480
        },
        "maxres": {
          "url": "https://i.ytimg.com/vi/ayOKJoYnREI/maxresdefault.jpg",
          "width": 1280,
          "height": 720
        }
      },
      "channelTitle": "The Woodlands Methodist Church",
      "playlistId": "PLgE8B1SdCTDshXW3ET6UHQQzav65px_Qx",
      "position": 2,
      "resourceId": {
        "kind": "youtube#video",
        "videoId": "ayOKJoYnREI"
      },
      "videoOwnerChannelTitle": "The Woodlands Methodist Church",
      "videoOwnerChannelId": "UClYsncuu6rBhsh2lYYb0zdQ"
    },
    "playlistName": "Loft"
  },
  {
    "kind": "youtube#playlistItem",
    "etag": "1rWNrxWE7B2fvuLXdeLOXYnAmJQ",
    "id": "UExnRThCMVNkQ1REdkJRYWxrMUNMSlE2dExqU3hzWHdmdy5FQUY2Qzk4RUFDN0ZFRkZF",
    "snippet": {
      "publishedAt": "2024-09-09T17:36:58Z",
      "channelId": "UClYsncuu6rBhsh2lYYb0zdQ",
      "title": "Exodus 1-2: The Story of Moses and God’s Plan for Life",
      "description": "In today’s message, we dive into the powerful story of Exodus chapters 1 and 2. We explore how Moses’ life was saved and how God used him to deliver His people from slavery. This story reminds us of God’s love and His plan for every life, no matter the circumstances. \n\nJoin us as we reflect on the importance of life, God’s guidance, and how His love can guide us through difficult times. \n\nThis message is especially relevant as we approach challenging conversations in our society. Let’s learn together how to love others as God loves us.",
      "thumbnails": {
        "default": {
          "url": "https://i.ytimg.com/vi/1xYR1F6JDBI/default.jpg",
          "width": 120,
          "height": 90
        },
        "medium": {
          "url": "https://i.ytimg.com/vi/1xYR1F6JDBI/mqdefault.jpg",
          "width": 320,
          "height": 180
        },
        "high": {
          "url": "https://i.ytimg.com/vi/1xYR1F6JDBI/hqdefault.jpg",
          "width": 480,
          "height": 360
        },
        "standard": {
          "url": "https://i.ytimg.com/vi/1xYR1F6JDBI/sddefault.jpg",
          "width": 640,
          "height": 480
        },
        "maxres": {
          "url": "https://i.ytimg.com/vi/1xYR1F6JDBI/maxresdefault.jpg",
          "width": 1280,
          "height": 720
        }
      },
      "channelTitle": "The Woodlands Methodist Church",
      "playlistId": "PLgE8B1SdCTDvBQalk1CLJQ6tLjSxsXwfw",
      "position": 0,
      "resourceId": {
        "kind": "youtube#video",
        "videoId": "1xYR1F6JDBI"
      },
      "videoOwnerChannelTitle": "The Woodlands Methodist Church",
      "videoOwnerChannelId": "UClYsncuu6rBhsh2lYYb0zdQ"
    },
    "playlistName": "Woodforest"
  },
  {
    "kind": "youtube#playlistItem",
    "etag": "xqZGnRye3yiljRYecZoq4gg4-t0",
    "id": "UExnRThCMVNkQ1REdkJRYWxrMUNMSlE2dExqU3hzWHdmdy4xN0Y2QjVBOEI2MzQ5OUM5",
    "snippet": {
      "publishedAt": "2024-09-03T16:59:49Z",
      "channelId": "UClYsncuu6rBhsh2lYYb0zdQ",
      "title": "Why Youth Leadership Matters: A Fresh Perspective on Faith",
      "description": "In this inspiring message, Pastor Brent challenges a common misconception in the church: that youth leadership is a lesser role. \n\nJoin us as we hear from Evan, a passionate young pastor, who shares his journey of faith and how the next generation is crucial to the future of the church. Evan reminds us that most people make a decision to follow Jesus before they turn 14, highlighting the importance of nurturing young believers. \n\nDon't miss this powerful sermon that encourages everyone, young and old, to stay spiritually awake and expectant for God's new work in their lives.",
      "thumbnails": {
        "default": {
          "url": "https://i.ytimg.com/vi/WtJmT_qmpsM/default.jpg",
          "width": 120,
          "height": 90
        },
        "medium": {
          "url": "https://i.ytimg.com/vi/WtJmT_qmpsM/mqdefault.jpg",
          "width": 320,
          "height": 180
        },
        "high": {
          "url": "https://i.ytimg.com/vi/WtJmT_qmpsM/hqdefault.jpg",
          "width": 480,
          "height": 360
        },
        "standard": {
          "url": "https://i.ytimg.com/vi/WtJmT_qmpsM/sddefault.jpg",
          "width": 640,
          "height": 480
        },
        "maxres": {
          "url": "https://i.ytimg.com/vi/WtJmT_qmpsM/maxresdefault.jpg",
          "width": 1280,
          "height": 720
        }
      },
      "channelTitle": "The Woodlands Methodist Church",
      "playlistId": "PLgE8B1SdCTDvBQalk1CLJQ6tLjSxsXwfw",
      "position": 1,
      "resourceId": {
        "kind": "youtube#video",
        "videoId": "WtJmT_qmpsM"
      },
      "videoOwnerChannelTitle": "The Woodlands Methodist Church",
      "videoOwnerChannelId": "UClYsncuu6rBhsh2lYYb0zdQ"
    },
    "playlistName": "Woodforest"
  },
  {
    "kind": "youtube#playlistItem",
    "etag": "Npwazufj3bjEaEtug4w55pczH2Q",
    "id": "UExnRThCMVNkQ1REdkJRYWxrMUNMSlE2dExqU3hzWHdmdy45NDlDQUFFOThDMTAxQjUw",
    "snippet": {
      "publishedAt": "2024-08-28T14:12:31Z",
      "channelId": "UClYsncuu6rBhsh2lYYb0zdQ",
      "title": "Finding Peace in Silence: A Journey Through Acts 28",
      "description": "In this message, we explore the final chapter of Acts, discovering how silence and reflection can bring us closer to God. Pastor Brent guides us through the practice of Lectio Divina – an ancient way of praying with Scripture – to help us open our hearts and minds to the Lord. \n\nAs we journey with Paul to the end of Acts, we learn the importance of listening to God, embracing His word, and understanding the role of the Church in God’s plan. Whether you’re facing storms in your life or simply seeking a deeper connection with God, this message offers hope and encouragement. \n\nJoin us as we learn to see with new eyes, hear with new ears, and soften our hearts to the voice of the Holy Spirit.",
      "thumbnails": {
        "default": {
          "url": "https://i.ytimg.com/vi/lZDXDQPZ0jM/default.jpg",
          "width": 120,
          "height": 90
        },
        "medium": {
          "url": "https://i.ytimg.com/vi/lZDXDQPZ0jM/mqdefault.jpg",
          "width": 320,
          "height": 180
        },
        "high": {
          "url": "https://i.ytimg.com/vi/lZDXDQPZ0jM/hqdefault.jpg",
          "width": 480,
          "height": 360
        },
        "standard": {
          "url": "https://i.ytimg.com/vi/lZDXDQPZ0jM/sddefault.jpg",
          "width": 640,
          "height": 480
        },
        "maxres": {
          "url": "https://i.ytimg.com/vi/lZDXDQPZ0jM/maxresdefault.jpg",
          "width": 1280,
          "height": 720
        }
      },
      "channelTitle": "The Woodlands Methodist Church",
      "playlistId": "PLgE8B1SdCTDvBQalk1CLJQ6tLjSxsXwfw",
      "position": 2,
      "resourceId": {
        "kind": "youtube#video",
        "videoId": "lZDXDQPZ0jM"
      },
      "videoOwnerChannelTitle": "The Woodlands Methodist Church",
      "videoOwnerChannelId": "UClYsncuu6rBhsh2lYYb0zdQ"
    },
    "playlistName": "Woodforest"
  },
  {
    "kind": "youtube#playlistItem",
    "etag": "JsnJl1c3wo6id53gh2BRCdvywxY",
    "id": "UExnRThCMVNkQ1REdHlrVldHTDc1bEpIUGhmblk1Q3FFRy5FQUY2Qzk4RUFDN0ZFRkZF",
    "snippet": {
      "publishedAt": "2024-09-09T17:29:27Z",
      "channelId": "UClYsncuu6rBhsh2lYYb0zdQ",
      "title": "Transforming Faith: Lessons from James the Brother of Jesus",
      "description": "In this inspiring sermon, we explore the journey of James, the brother of Jesus, from skeptic to leader in the early church. Discover how James’s life changed after seeing the risen Christ and how his story teaches us that faith is more than just believing—it's about living out our beliefs through our actions. \n\nJoin us as we dive into the wisdom of James and learn how to make a difference in our community by following Christ’s example. \n\nWhether you're a long-time believer or just starting your faith journey, this message will encourage you to walk the walk and serve with joy.",
      "thumbnails": {
        "default": {
          "url": "https://i.ytimg.com/vi/tDyU11JG2jk/default.jpg",
          "width": 120,
          "height": 90
        },
        "medium": {
          "url": "https://i.ytimg.com/vi/tDyU11JG2jk/mqdefault.jpg",
          "width": 320,
          "height": 180
        },
        "high": {
          "url": "https://i.ytimg.com/vi/tDyU11JG2jk/hqdefault.jpg",
          "width": 480,
          "height": 360
        },
        "standard": {
          "url": "https://i.ytimg.com/vi/tDyU11JG2jk/sddefault.jpg",
          "width": 640,
          "height": 480
        },
        "maxres": {
          "url": "https://i.ytimg.com/vi/tDyU11JG2jk/maxresdefault.jpg",
          "width": 1280,
          "height": 720
        }
      },
      "channelTitle": "The Woodlands Methodist Church",
      "playlistId": "PLgE8B1SdCTDtykVWGL75lJHPhfnY5CqEG",
      "position": 0,
      "resourceId": {
        "kind": "youtube#video",
        "videoId": "tDyU11JG2jk"
      },
      "videoOwnerChannelTitle": "The Woodlands Methodist Church",
      "videoOwnerChannelId": "UClYsncuu6rBhsh2lYYb0zdQ"
    },
    "playlistName": "Traditional"
  },
  {
    "kind": "youtube#playlistItem",
    "etag": "WRhJlw57xnStJe4PLwIHXN0Gc_g",
    "id": "UExnRThCMVNkQ1REdHlrVldHTDc1bEpIUGhmblk1Q3FFRy4xN0Y2QjVBOEI2MzQ5OUM5",
    "snippet": {
      "publishedAt": "2024-09-03T17:05:01Z",
      "channelId": "UClYsncuu6rBhsh2lYYb0zdQ",
      "title": "Humility: The Hidden Power in a Christian’s Life",
      "description": "Discover what the Bible teaches about this often misunderstood virtue and how it can transform your life. Learn why true humility isn't about thinking less of yourself, but about thinking of yourself less. \n\nThrough Scripture, stories, and the wisdom of Christian leaders, we explore how embracing humility can bring you closer to God and free you from the burdens of pride and self-centeredness. \n\nPerfect for anyone looking to grow in their faith and understanding of God's Word.",
      "thumbnails": {
        "default": {
          "url": "https://i.ytimg.com/vi/7s7FjdpMfhA/default.jpg",
          "width": 120,
          "height": 90
        },
        "medium": {
          "url": "https://i.ytimg.com/vi/7s7FjdpMfhA/mqdefault.jpg",
          "width": 320,
          "height": 180
        },
        "high": {
          "url": "https://i.ytimg.com/vi/7s7FjdpMfhA/hqdefault.jpg",
          "width": 480,
          "height": 360
        },
        "standard": {
          "url": "https://i.ytimg.com/vi/7s7FjdpMfhA/sddefault.jpg",
          "width": 640,
          "height": 480
        },
        "maxres": {
          "url": "https://i.ytimg.com/vi/7s7FjdpMfhA/maxresdefault.jpg",
          "width": 1280,
          "height": 720
        }
      },
      "channelTitle": "The Woodlands Methodist Church",
      "playlistId": "PLgE8B1SdCTDtykVWGL75lJHPhfnY5CqEG",
      "position": 1,
      "resourceId": {
        "kind": "youtube#video",
        "videoId": "7s7FjdpMfhA"
      },
      "videoOwnerChannelTitle": "The Woodlands Methodist Church",
      "videoOwnerChannelId": "UClYsncuu6rBhsh2lYYb0zdQ"
    },
    "playlistName": "Traditional"
  },
  {
    "kind": "youtube#playlistItem",
    "etag": "er9uJ_19e_gjL3_JPSf6UyGHVbM",
    "id": "UExnRThCMVNkQ1REdHlrVldHTDc1bEpIUGhmblk1Q3FFRy45NDlDQUFFOThDMTAxQjUw",
    "snippet": {
      "publishedAt": "2024-08-28T14:10:06Z",
      "channelId": "UClYsncuu6rBhsh2lYYb0zdQ",
      "title": "Wisdom and Love: God’s Greatest Rewards",
      "description": "In this sermon from The Woodlands Methodist Church, Bishop Bob Hayes explores the powerful connection between God’s love and true wisdom. Through the story of Solomon, who chose wisdom over wealth, we learn that real wisdom comes from understanding God’s love. \n\nJoin us as we unpack how love and wisdom go hand-in-hand, shaping our lives and guiding our decisions. By embracing God’s love, we find peace, purpose, and the ultimate reward — a life that reflects Jesus. \n\nLet’s grow together in love and wisdom as we live out God’s calling.",
      "thumbnails": {
        "default": {
          "url": "https://i.ytimg.com/vi/tl3iHNJubKc/default.jpg",
          "width": 120,
          "height": 90
        },
        "medium": {
          "url": "https://i.ytimg.com/vi/tl3iHNJubKc/mqdefault.jpg",
          "width": 320,
          "height": 180
        },
        "high": {
          "url": "https://i.ytimg.com/vi/tl3iHNJubKc/hqdefault.jpg",
          "width": 480,
          "height": 360
        },
        "standard": {
          "url": "https://i.ytimg.com/vi/tl3iHNJubKc/sddefault.jpg",
          "width": 640,
          "height": 480
        },
        "maxres": {
          "url": "https://i.ytimg.com/vi/tl3iHNJubKc/maxresdefault.jpg",
          "width": 1280,
          "height": 720
        }
      },
      "channelTitle": "The Woodlands Methodist Church",
      "playlistId": "PLgE8B1SdCTDtykVWGL75lJHPhfnY5CqEG",
      "position": 2,
      "resourceId": {
        "kind": "youtube#video",
        "videoId": "tl3iHNJubKc"
      },
      "videoOwnerChannelTitle": "The Woodlands Methodist Church",
      "videoOwnerChannelId": "UClYsncuu6rBhsh2lYYb0zdQ"
    },
    "playlistName": "Traditional"
  },
  {
    "kind": "youtube#playlistItem",
    "etag": "sUudlQWteBAFMmmKFB9Lp-lh3Gs",
    "id": "UExnRThCMVNkQ1REdmM4T2dwNkxjZWQ1eUNmN3g5LUpKQi4wMDFGNzBEOTU4Q0Y1Q0RG",
    "snippet": {
      "publishedAt": "2024-09-09T17:39:39Z",
      "channelId": "UClYsncuu6rBhsh2lYYb0zdQ",
      "title": "Unlocking Revelation: Exploring the Throne Room of God",
      "description": "In this powerful sermon, we dive into Revelation chapters 4 and 5, discovering the awe-inspiring vision John had of the throne room of God. Imagine seeing a grand throne surrounded by dazzling lights and colors, where heavenly beings worship God day and night. This message explores how these chapters reveal the majesty and authority of God and the Lamb who is worthy to open the scrolls. \n\nWhether you’re new to the Bible or have been studying it for years, join us as we explore these crucial chapters and their significance for us today. You’ll be encouraged to see how your prayers and worship fit into this grand vision and how God is still on the throne, no matter what challenges we face.",
      "thumbnails": {
        "default": {
          "url": "https://i.ytimg.com/vi/dFfjyjNTS7E/default.jpg",
          "width": 120,
          "height": 90
        },
        "medium": {
          "url": "https://i.ytimg.com/vi/dFfjyjNTS7E/mqdefault.jpg",
          "width": 320,
          "height": 180
        },
        "high": {
          "url": "https://i.ytimg.com/vi/dFfjyjNTS7E/hqdefault.jpg",
          "width": 480,
          "height": 360
        },
        "standard": {
          "url": "https://i.ytimg.com/vi/dFfjyjNTS7E/sddefault.jpg",
          "width": 640,
          "height": 480
        },
        "maxres": {
          "url": "https://i.ytimg.com/vi/dFfjyjNTS7E/maxresdefault.jpg",
          "width": 1280,
          "height": 720
        }
      },
      "channelTitle": "The Woodlands Methodist Church",
      "playlistId": "PLgE8B1SdCTDvc8Ogp6Lced5yCf7x9-JJB",
      "position": 0,
      "resourceId": {
        "kind": "youtube#video",
        "videoId": "dFfjyjNTS7E"
      },
      "videoOwnerChannelTitle": "The Woodlands Methodist Church",
      "videoOwnerChannelId": "UClYsncuu6rBhsh2lYYb0zdQ"
    },
    "playlistName": "Harvest"
  },
  {
    "kind": "youtube#playlistItem",
    "etag": "1ZCLZ4BGIBIl7BEFDUfA9aL5pp4",
    "id": "UExnRThCMVNkQ1REdmM4T2dwNkxjZWQ1eUNmN3g5LUpKQi4xNTZBNUQxMDZBQzFGMjkw",
    "snippet": {
      "publishedAt": "2024-09-03T16:57:55Z",
      "channelId": "UClYsncuu6rBhsh2lYYb0zdQ",
      "title": "Prepare Your Heart: The Call to Radical Holiness",
      "description": "In this powerful sermon, we explore the deep message of God’s call to radical holiness. As we journey through Revelation, we are reminded of the churches that received both praise and rebuke. What does it mean to be lukewarm, and how does God’s rebuke reflect His love for us? \n\nThis message will challenge you to reflect on your own life and encourage you to embrace a life of holiness, knowing that God’s correction is a sign of His love and presence. \n\nLet’s open our hearts to His call and prepare for the coming of His Kingdom.",
      "thumbnails": {
        "default": {
          "url": "https://i.ytimg.com/vi/jv4vF1iMpII/default.jpg",
          "width": 120,
          "height": 90
        },
        "medium": {
          "url": "https://i.ytimg.com/vi/jv4vF1iMpII/mqdefault.jpg",
          "width": 320,
          "height": 180
        },
        "high": {
          "url": "https://i.ytimg.com/vi/jv4vF1iMpII/hqdefault.jpg",
          "width": 480,
          "height": 360
        },
        "standard": {
          "url": "https://i.ytimg.com/vi/jv4vF1iMpII/sddefault.jpg",
          "width": 640,
          "height": 480
        },
        "maxres": {
          "url": "https://i.ytimg.com/vi/jv4vF1iMpII/maxresdefault.jpg",
          "width": 1280,
          "height": 720
        }
      },
      "channelTitle": "The Woodlands Methodist Church",
      "playlistId": "PLgE8B1SdCTDvc8Ogp6Lced5yCf7x9-JJB",
      "position": 1,
      "resourceId": {
        "kind": "youtube#video",
        "videoId": "jv4vF1iMpII"
      },
      "videoOwnerChannelTitle": "The Woodlands Methodist Church",
      "videoOwnerChannelId": "UClYsncuu6rBhsh2lYYb0zdQ"
    },
    "playlistName": "Harvest"
  },
  {
    "kind": "youtube#playlistItem",
    "etag": "9wZAyUVTanrmuZdAwblC2cWpA4w",
    "id": "UExnRThCMVNkQ1REdmM4T2dwNkxjZWQ1eUNmN3g5LUpKQi4zQTkzRjgxRTY0OEU0MkM3",
    "snippet": {
      "publishedAt": "2024-08-28T14:11:28Z",
      "channelId": "UClYsncuu6rBhsh2lYYb0zdQ",
      "title": "Revelation Unveiled: Jesus’ Message to the Suffering Church",
      "description": "In this sermon, we dive into the Book of Revelation and explore Jesus’ powerful message to the church of Smyrna — a church enduring intense suffering and persecution. Jesus reminds them that He knows their tribulations and encourages them to stand firm in their faith. \n\nAs we study this passage, we learn how to apply these truths to our lives today, finding hope and strength in the midst of our own trials. \n\nJoin us as we unpack the lessons from Smyrna and discover how Jesus walks with us through every challenge, offering comfort and promise to those who remain faithful.",
      "thumbnails": {
        "default": {
          "url": "https://i.ytimg.com/vi/JuRGtMSNkI0/default.jpg",
          "width": 120,
          "height": 90
        },
        "medium": {
          "url": "https://i.ytimg.com/vi/JuRGtMSNkI0/mqdefault.jpg",
          "width": 320,
          "height": 180
        },
        "high": {
          "url": "https://i.ytimg.com/vi/JuRGtMSNkI0/hqdefault.jpg",
          "width": 480,
          "height": 360
        },
        "standard": {
          "url": "https://i.ytimg.com/vi/JuRGtMSNkI0/sddefault.jpg",
          "width": 640,
          "height": 480
        },
        "maxres": {
          "url": "https://i.ytimg.com/vi/JuRGtMSNkI0/maxresdefault.jpg",
          "width": 1280,
          "height": 720
        }
      },
      "channelTitle": "The Woodlands Methodist Church",
      "playlistId": "PLgE8B1SdCTDvc8Ogp6Lced5yCf7x9-JJB",
      "position": 2,
      "resourceId": {
        "kind": "youtube#video",
        "videoId": "JuRGtMSNkI0"
      },
      "videoOwnerChannelTitle": "The Woodlands Methodist Church",
      "videoOwnerChannelId": "UClYsncuu6rBhsh2lYYb0zdQ"
    },
    "playlistName": "Harvest"
  },
  {
    "kind": "youtube#playlistItem",
    "etag": "1rWNrxWE7B2fvuLXdeLOXYnAmJQ",
    "id": "UExnRThCMVNkQ1REdkJRYWxrMUNMSlE2dExqU3hzWHdmdy5FQUY2Qzk4RUFDN0ZFRkZF",
    "snippet": {
      "publishedAt": "2024-09-09T17:36:58Z",
      "channelId": "UClYsncuu6rBhsh2lYYb0zdQ",
      "title": "Exodus 1-2: The Story of Moses and God’s Plan for Life",
      "description": "In today’s message, we dive into the powerful story of Exodus chapters 1 and 2. We explore how Moses’ life was saved and how God used him to deliver His people from slavery. This story reminds us of God’s love and His plan for every life, no matter the circumstances. \n\nJoin us as we reflect on the importance of life, God’s guidance, and how His love can guide us through difficult times. \n\nThis message is especially relevant as we approach challenging conversations in our society. Let’s learn together how to love others as God loves us.",
      "thumbnails": {
        "default": {
          "url": "https://i.ytimg.com/vi/1xYR1F6JDBI/default.jpg",
          "width": 120,
          "height": 90
        },
        "medium": {
          "url": "https://i.ytimg.com/vi/1xYR1F6JDBI/mqdefault.jpg",
          "width": 320,
          "height": 180
        },
        "high": {
          "url": "https://i.ytimg.com/vi/1xYR1F6JDBI/hqdefault.jpg",
          "width": 480,
          "height": 360
        },
        "standard": {
          "url": "https://i.ytimg.com/vi/1xYR1F6JDBI/sddefault.jpg",
          "width": 640,
          "height": 480
        },
        "maxres": {
          "url": "https://i.ytimg.com/vi/1xYR1F6JDBI/maxresdefault.jpg",
          "width": 1280,
          "height": 720
        }
      },
      "channelTitle": "The Woodlands Methodist Church",
      "playlistId": "PLgE8B1SdCTDvBQalk1CLJQ6tLjSxsXwfw",
      "position": 0,
      "resourceId": {
        "kind": "youtube#video",
        "videoId": "1xYR1F6JDBI"
      },
      "videoOwnerChannelTitle": "The Woodlands Methodist Church",
      "videoOwnerChannelId": "UClYsncuu6rBhsh2lYYb0zdQ"
    },
    "playlistName": "Church at Woodforest"
  },
  {
    "kind": "youtube#playlistItem",
    "etag": "xqZGnRye3yiljRYecZoq4gg4-t0",
    "id": "UExnRThCMVNkQ1REdkJRYWxrMUNMSlE2dExqU3hzWHdmdy4xN0Y2QjVBOEI2MzQ5OUM5",
    "snippet": {
      "publishedAt": "2024-09-03T16:59:49Z",
      "channelId": "UClYsncuu6rBhsh2lYYb0zdQ",
      "title": "Why Youth Leadership Matters: A Fresh Perspective on Faith",
      "description": "In this inspiring message, Pastor Brent challenges a common misconception in the church: that youth leadership is a lesser role. \n\nJoin us as we hear from Evan, a passionate young pastor, who shares his journey of faith and how the next generation is crucial to the future of the church. Evan reminds us that most people make a decision to follow Jesus before they turn 14, highlighting the importance of nurturing young believers. \n\nDon't miss this powerful sermon that encourages everyone, young and old, to stay spiritually awake and expectant for God's new work in their lives.",
      "thumbnails": {
        "default": {
          "url": "https://i.ytimg.com/vi/WtJmT_qmpsM/default.jpg",
          "width": 120,
          "height": 90
        },
        "medium": {
          "url": "https://i.ytimg.com/vi/WtJmT_qmpsM/mqdefault.jpg",
          "width": 320,
          "height": 180
        },
        "high": {
          "url": "https://i.ytimg.com/vi/WtJmT_qmpsM/hqdefault.jpg",
          "width": 480,
          "height": 360
        },
        "standard": {
          "url": "https://i.ytimg.com/vi/WtJmT_qmpsM/sddefault.jpg",
          "width": 640,
          "height": 480
        },
        "maxres": {
          "url": "https://i.ytimg.com/vi/WtJmT_qmpsM/maxresdefault.jpg",
          "width": 1280,
          "height": 720
        }
      },
      "channelTitle": "The Woodlands Methodist Church",
      "playlistId": "PLgE8B1SdCTDvBQalk1CLJQ6tLjSxsXwfw",
      "position": 1,
      "resourceId": {
        "kind": "youtube#video",
        "videoId": "WtJmT_qmpsM"
      },
      "videoOwnerChannelTitle": "The Woodlands Methodist Church",
      "videoOwnerChannelId": "UClYsncuu6rBhsh2lYYb0zdQ"
    },
    "playlistName": "Church at Woodforest"
  },
  {
    "kind": "youtube#playlistItem",
    "etag": "Npwazufj3bjEaEtug4w55pczH2Q",
    "id": "UExnRThCMVNkQ1REdkJRYWxrMUNMSlE2dExqU3hzWHdmdy45NDlDQUFFOThDMTAxQjUw",
    "snippet": {
      "publishedAt": "2024-08-28T14:12:31Z",
      "channelId": "UClYsncuu6rBhsh2lYYb0zdQ",
      "title": "Finding Peace in Silence: A Journey Through Acts 28",
      "description": "In this message, we explore the final chapter of Acts, discovering how silence and reflection can bring us closer to God. Pastor Brent guides us through the practice of Lectio Divina – an ancient way of praying with Scripture – to help us open our hearts and minds to the Lord. \n\nAs we journey with Paul to the end of Acts, we learn the importance of listening to God, embracing His word, and understanding the role of the Church in God’s plan. Whether you’re facing storms in your life or simply seeking a deeper connection with God, this message offers hope and encouragement. \n\nJoin us as we learn to see with new eyes, hear with new ears, and soften our hearts to the voice of the Holy Spirit.",
      "thumbnails": {
        "default": {
          "url": "https://i.ytimg.com/vi/lZDXDQPZ0jM/default.jpg",
          "width": 120,
          "height": 90
        },
        "medium": {
          "url": "https://i.ytimg.com/vi/lZDXDQPZ0jM/mqdefault.jpg",
          "width": 320,
          "height": 180
        },
        "high": {
          "url": "https://i.ytimg.com/vi/lZDXDQPZ0jM/hqdefault.jpg",
          "width": 480,
          "height": 360
        },
        "standard": {
          "url": "https://i.ytimg.com/vi/lZDXDQPZ0jM/sddefault.jpg",
          "width": 640,
          "height": 480
        },
        "maxres": {
          "url": "https://i.ytimg.com/vi/lZDXDQPZ0jM/maxresdefault.jpg",
          "width": 1280,
          "height": 720
        }
      },
      "channelTitle": "The Woodlands Methodist Church",
      "playlistId": "PLgE8B1SdCTDvBQalk1CLJQ6tLjSxsXwfw",
      "position": 2,
      "resourceId": {
        "kind": "youtube#video",
        "videoId": "lZDXDQPZ0jM"
      },
      "videoOwnerChannelTitle": "The Woodlands Methodist Church",
      "videoOwnerChannelId": "UClYsncuu6rBhsh2lYYb0zdQ"
    },
    "playlistName": "Church at Woodforest"
  },
  {
    "kind": "youtube#playlistItem",
    "etag": "x3JNVrPxMItjvEySdqPYjxbkEmw",
    "id": "UExnRThCMVNkQ1REdk14Y040d1VjaXR0UmpxRjhFeTFFeS5GM0Q3M0MzMzY5NTJFNTdE",
    "snippet": {
      "publishedAt": "2024-09-09T17:38:49Z",
      "channelId": "UClYsncuu6rBhsh2lYYb0zdQ",
      "title": "Finding Hope in the Dark Times: How to Feed the Wolf of Hope",
      "description": "In today’s message, we explore the powerful role of hope in our lives, especially during tough times. Just like people search for miraculous treatments, we all look for hope to overcome our challenges. Whether you're struggling with illness, feeling down, or just trying to stay positive, hope is essential for our well-being.\n\nJoin us as we discuss:\n* How hope helps us face the future.\n* Personal stories of battling hopelessness.\n* Practical steps to feed hope into our lives, including sharing with others, turning to God’s word, practicing gratitude, and always looking forward.\n\nWe’ll discover how hope is like the oxygen for our spirit and how we can cultivate it even when it feels out of reach. Remember, you’re not alone—let’s find hope together!",
      "thumbnails": {
        "default": {
          "url": "https://i.ytimg.com/vi/IoMses1YAgc/default.jpg",
          "width": 120,
          "height": 90
        },
        "medium": {
          "url": "https://i.ytimg.com/vi/IoMses1YAgc/mqdefault.jpg",
          "width": 320,
          "height": 180
        },
        "high": {
          "url": "https://i.ytimg.com/vi/IoMses1YAgc/hqdefault.jpg",
          "width": 480,
          "height": 360
        },
        "standard": {
          "url": "https://i.ytimg.com/vi/IoMses1YAgc/sddefault.jpg",
          "width": 640,
          "height": 480
        },
        "maxres": {
          "url": "https://i.ytimg.com/vi/IoMses1YAgc/maxresdefault.jpg",
          "width": 1280,
          "height": 720
        }
      },
      "channelTitle": "The Woodlands Methodist Church",
      "playlistId": "PLgE8B1SdCTDvMxcN4wUcittRjqF8Ey1Ey",
      "position": 21,
      "resourceId": {
        "kind": "youtube#video",
        "videoId": "IoMses1YAgc"
      },
      "videoOwnerChannelTitle": "The Woodlands Methodist Church",
      "videoOwnerChannelId": "UClYsncuu6rBhsh2lYYb0zdQ"
    },
    "playlistName": "Rev. Luann Riley"
  },
  {
    "kind": "youtube#playlistItem",
    "etag": "i-Q8dK_eu1ovbm6VeHuYrXxAZDg",
    "id": "UExnRThCMVNkQ1REdVRhbndpbE0zcE9WdmNHRE45dXlMWS4zRjM0MkVCRTg0MkYyQTM0",
    "snippet": {
      "publishedAt": "2024-09-03T16:58:39Z",
      "channelId": "UClYsncuu6rBhsh2lYYb0zdQ",
      "title": "Prepare Your Heart: The Call to Radical Holiness",
      "description": "In this powerful sermon, we explore the deep message of God’s call to radical holiness. As we journey through Revelation, we are reminded of the churches that received both praise and rebuke. What does it mean to be lukewarm, and how does God’s rebuke reflect His love for us? \n\nThis message will challenge you to reflect on your own life and encourage you to embrace a life of holiness, knowing that God’s correction is a sign of His love and presence. \n\nLet’s open our hearts to His call and prepare for the coming of His Kingdom.",
      "thumbnails": {
        "default": {
          "url": "https://i.ytimg.com/vi/jv4vF1iMpII/default.jpg",
          "width": 120,
          "height": 90
        },
        "medium": {
          "url": "https://i.ytimg.com/vi/jv4vF1iMpII/mqdefault.jpg",
          "width": 320,
          "height": 180
        },
        "high": {
          "url": "https://i.ytimg.com/vi/jv4vF1iMpII/hqdefault.jpg",
          "width": 480,
          "height": 360
        },
        "standard": {
          "url": "https://i.ytimg.com/vi/jv4vF1iMpII/sddefault.jpg",
          "width": 640,
          "height": 480
        },
        "maxres": {
          "url": "https://i.ytimg.com/vi/jv4vF1iMpII/maxresdefault.jpg",
          "width": 1280,
          "height": 720
        }
      },
      "channelTitle": "The Woodlands Methodist Church",
      "playlistId": "PLgE8B1SdCTDuTanwilM3pOVvcGDN9uyLY",
      "position": 22,
      "resourceId": {
        "kind": "youtube#video",
        "videoId": "jv4vF1iMpII"
      },
      "videoOwnerChannelTitle": "The Woodlands Methodist Church",
      "videoOwnerChannelId": "UClYsncuu6rBhsh2lYYb0zdQ"
    },
    "playlistName": "Pierce Drake"
  },
  {
    "kind": "youtube#playlistItem",
    "etag": "KMiQmek58U7JJTigc51fupE4aW4",
    "id": "UExKaHZqQW1IZ2tBbzR6YXdzd2FraGxicmM5bm9xWjJMWC41MjE1MkI0OTQ2QzJGNzNG",
    "snippet": {
      "publishedAt": "2024-09-09T16:47:34Z",
      "channelId": "UCva_VP1jypeRBjO66q9Pu_Q",
      "title": "Unlocking Revelation: Exploring the Throne Room of God",
      "description": "In this powerful sermon, we dive into Revelation chapters 4 and 5, discovering the awe-inspiring vision John had of the throne room of God. Imagine seeing a grand throne surrounded by dazzling lights and colors, where heavenly beings worship God day and night. This message explores how these chapters reveal the majesty and authority of God and the Lamb who is worthy to open the scrolls. \n\nWhether you’re new to the Bible or have been studying it for years, join us as we explore these crucial chapters and their significance for us today. You’ll be encouraged to see how your prayers and worship fit into this grand vision and how God is still on the throne, no matter what challenges we face.",
      "thumbnails": {
        "default": {
          "url": "https://i.ytimg.com/vi/SrX8xSkidUM/default.jpg",
          "width": 120,
          "height": 90
        },
        "medium": {
          "url": "https://i.ytimg.com/vi/SrX8xSkidUM/mqdefault.jpg",
          "width": 320,
          "height": 180
        },
        "high": {
          "url": "https://i.ytimg.com/vi/SrX8xSkidUM/hqdefault.jpg",
          "width": 480,
          "height": 360
        },
        "standard": {
          "url": "https://i.ytimg.com/vi/SrX8xSkidUM/sddefault.jpg",
          "width": 640,
          "height": 480
        },
        "maxres": {
          "url": "https://i.ytimg.com/vi/SrX8xSkidUM/maxresdefault.jpg",
          "width": 1280,
          "height": 720
        }
      },
      "channelTitle": "Harvest TWMC",
      "playlistId": "PLJhvjAmHgkAo4zawswakhlbrc9noqZ2LX",
      "position": 0,
      "resourceId": {
        "kind": "youtube#video",
        "videoId": "SrX8xSkidUM"
      },
      "videoOwnerChannelTitle": "Harvest TWMC",
      "videoOwnerChannelId": "UCva_VP1jypeRBjO66q9Pu_Q"
    },
    "playlistName": "Revelation"
  },
  {
    "kind": "youtube#playlistItem",
    "etag": "SPOsMUjD8_Qy3gyqRiSScOX9XlA",
    "id": "UExKaHZqQW1IZ2tBbzR6YXdzd2FraGxicmM5bm9xWjJMWC4wMTcyMDhGQUE4NTIzM0Y5",
    "snippet": {
      "publishedAt": "2024-09-03T16:56:57Z",
      "channelId": "UCva_VP1jypeRBjO66q9Pu_Q",
      "title": "Prepare Your Heart: The Call to Radical Holiness",
      "description": "In this powerful sermon, we explore the deep message of God’s call to radical holiness. As we journey through Revelation, we are reminded of the churches that received both praise and rebuke. What does it mean to be lukewarm, and how does God’s rebuke reflect His love for us? \n\nThis message will challenge you to reflect on your own life and encourage you to embrace a life of holiness, knowing that God’s correction is a sign of His love and presence. \n\nLet’s open our hearts to His call and prepare for the coming of His Kingdom.",
      "thumbnails": {
        "default": {
          "url": "https://i.ytimg.com/vi/e0m78AChYQY/default.jpg",
          "width": 120,
          "height": 90
        },
        "medium": {
          "url": "https://i.ytimg.com/vi/e0m78AChYQY/mqdefault.jpg",
          "width": 320,
          "height": 180
        },
        "high": {
          "url": "https://i.ytimg.com/vi/e0m78AChYQY/hqdefault.jpg",
          "width": 480,
          "height": 360
        },
        "standard": {
          "url": "https://i.ytimg.com/vi/e0m78AChYQY/sddefault.jpg",
          "width": 640,
          "height": 480
        },
        "maxres": {
          "url": "https://i.ytimg.com/vi/e0m78AChYQY/maxresdefault.jpg",
          "width": 1280,
          "height": 720
        }
      },
      "channelTitle": "Harvest TWMC",
      "playlistId": "PLJhvjAmHgkAo4zawswakhlbrc9noqZ2LX",
      "position": 1,
      "resourceId": {
        "kind": "youtube#video",
        "videoId": "e0m78AChYQY"
      },
      "videoOwnerChannelTitle": "Harvest TWMC",
      "videoOwnerChannelId": "UCva_VP1jypeRBjO66q9Pu_Q"
    },
    "playlistName": "Revelation"
  },
  {
    "kind": "youtube#playlistItem",
    "etag": "3x6jmG7pMqLKU0dDs7-adqzPdG8",
    "id": "UExNUnp2MmpPeGhmUVAtMU1tYnV2dExZZEdiSDRKcldfSi5DMTA0RkI2RTNGNUQ0Njgw",
    "snippet": {
      "publishedAt": "2024-09-09T16:18:17Z",
      "channelId": "UCP7ezytRb2i4njgDxhwHFTg",
      "title": "Exodus 1-2: The Story of Moses and God’s Plan for Life",
      "description": "In today’s message, we dive into the powerful story of Exodus chapters 1 and 2. We explore how Moses’ life was saved and how God used him to deliver His people from slavery. This story reminds us of God’s love and His plan for every life, no matter the circumstances. \n\nJoin us as we reflect on the importance of life, God’s guidance, and how His love can guide us through difficult times. \n\nThis message is especially relevant as we approach challenging conversations in our society. Let’s learn together how to love others as God loves us.",
      "thumbnails": {
        "default": {
          "url": "https://i.ytimg.com/vi/R2i-wxe6oaE/default.jpg",
          "width": 120,
          "height": 90
        },
        "medium": {
          "url": "https://i.ytimg.com/vi/R2i-wxe6oaE/mqdefault.jpg",
          "width": 320,
          "height": 180
        },
        "high": {
          "url": "https://i.ytimg.com/vi/R2i-wxe6oaE/hqdefault.jpg",
          "width": 480,
          "height": 360
        },
        "standard": {
          "url": "https://i.ytimg.com/vi/R2i-wxe6oaE/sddefault.jpg",
          "width": 640,
          "height": 480
        },
        "maxres": {
          "url": "https://i.ytimg.com/vi/R2i-wxe6oaE/maxresdefault.jpg",
          "width": 1280,
          "height": 720
        }
      },
      "channelTitle": "The Church at Woodforest",
      "playlistId": "PLMRzv2jOxhfQP-1MmbuvtLYdGbH4JrW_J",
      "position": 0,
      "resourceId": {
        "kind": "youtube#video",
        "videoId": "R2i-wxe6oaE"
      },
      "videoOwnerChannelTitle": "The Church at Woodforest",
      "videoOwnerChannelId": "UCP7ezytRb2i4njgDxhwHFTg"
    },
    "playlistName": "Latest Sermons"
  },
  {
    "kind": "youtube#playlistItem",
    "etag": "NUC_Y40gmopqf1jr0hGWE-RaSxg",
    "id": "UExNUnp2MmpPeGhmUVAtMU1tYnV2dExZZEdiSDRKcldfSi45REM1NzQ1MDM2OUZDNDMx",
    "snippet": {
      "publishedAt": "2024-09-03T16:31:43Z",
      "channelId": "UCP7ezytRb2i4njgDxhwHFTg",
      "title": "Why Youth Leadership Matters: A Fresh Perspective on Faith",
      "description": "In this inspiring message, Pastor Brent challenges a common misconception in the church: that youth leadership is a lesser role. \n\nJoin us as we hear from Evan, a passionate young pastor, who shares his journey of faith and how the next generation is crucial to the future of the church. Evan reminds us that most people make a decision to follow Jesus before they turn 14, highlighting the importance of nurturing young believers. \n\nDon't miss this powerful sermon that encourages everyone, young and old, to stay spiritually awake and expectant for God's new work in their lives.",
      "thumbnails": {
        "default": {
          "url": "https://i.ytimg.com/vi/GpXf31dtaTI/default.jpg",
          "width": 120,
          "height": 90
        },
        "medium": {
          "url": "https://i.ytimg.com/vi/GpXf31dtaTI/mqdefault.jpg",
          "width": 320,
          "height": 180
        },
        "high": {
          "url": "https://i.ytimg.com/vi/GpXf31dtaTI/hqdefault.jpg",
          "width": 480,
          "height": 360
        },
        "standard": {
          "url": "https://i.ytimg.com/vi/GpXf31dtaTI/sddefault.jpg",
          "width": 640,
          "height": 480
        },
        "maxres": {
          "url": "https://i.ytimg.com/vi/GpXf31dtaTI/maxresdefault.jpg",
          "width": 1280,
          "height": 720
        }
      },
      "channelTitle": "The Church at Woodforest",
      "playlistId": "PLMRzv2jOxhfQP-1MmbuvtLYdGbH4JrW_J",
      "position": 1,
      "resourceId": {
        "kind": "youtube#video",
        "videoId": "GpXf31dtaTI"
      },
      "videoOwnerChannelTitle": "The Church at Woodforest",
      "videoOwnerChannelId": "UCP7ezytRb2i4njgDxhwHFTg"
    },
    "playlistName": "Latest Sermons"
  },
  {
    "kind": "youtube#playlistItem",
    "etag": "DKnQ0Rp_xip4MsGzUqlfZjOjt8U",
    "id": "UExNUnp2MmpPeGhmVFdhR3k5MjhhaVRWOXUwTVV5NHRLLS4wQjA4QkVEQ0RFREIzMjFC",
    "snippet": {
      "publishedAt": "2024-09-09T16:18:17Z",
      "channelId": "UCP7ezytRb2i4njgDxhwHFTg",
      "title": "Exodus 1-2: The Story of Moses and God’s Plan for Life",
      "description": "In today’s message, we dive into the powerful story of Exodus chapters 1 and 2. We explore how Moses’ life was saved and how God used him to deliver His people from slavery. This story reminds us of God’s love and His plan for every life, no matter the circumstances. \n\nJoin us as we reflect on the importance of life, God’s guidance, and how His love can guide us through difficult times. \n\nThis message is especially relevant as we approach challenging conversations in our society. Let’s learn together how to love others as God loves us.",
      "thumbnails": {
        "default": {
          "url": "https://i.ytimg.com/vi/R2i-wxe6oaE/default.jpg",
          "width": 120,
          "height": 90
        },
        "medium": {
          "url": "https://i.ytimg.com/vi/R2i-wxe6oaE/mqdefault.jpg",
          "width": 320,
          "height": 180
        },
        "high": {
          "url": "https://i.ytimg.com/vi/R2i-wxe6oaE/hqdefault.jpg",
          "width": 480,
          "height": 360
        },
        "standard": {
          "url": "https://i.ytimg.com/vi/R2i-wxe6oaE/sddefault.jpg",
          "width": 640,
          "height": 480
        },
        "maxres": {
          "url": "https://i.ytimg.com/vi/R2i-wxe6oaE/maxresdefault.jpg",
          "width": 1280,
          "height": 720
        }
      },
      "channelTitle": "The Church at Woodforest",
      "playlistId": "PLMRzv2jOxhfTWaGy928aiTV9u0MUy4tK-",
      "position": 138,
      "resourceId": {
        "kind": "youtube#video",
        "videoId": "R2i-wxe6oaE"
      },
      "videoOwnerChannelTitle": "The Church at Woodforest",
      "videoOwnerChannelId": "UCP7ezytRb2i4njgDxhwHFTg"
    },
    "playlistName": "Brent Parker"
  },
  {
    "kind": "youtube#playlistItem",
    "etag": "J-Pr3XR10ChnpG25MC-BGhattOs",
    "id": "UExNUnp2MmpPeGhmUmpNTU5LVjNzQWdQU0wwZl9mdnBGeC41MzY4MzcwOUFFRUU3QzEx",
    "snippet": {
      "publishedAt": "2024-09-03T16:31:43Z",
      "channelId": "UCP7ezytRb2i4njgDxhwHFTg",
      "title": "Why Youth Leadership Matters: A Fresh Perspective on Faith",
      "description": "In this inspiring message, Pastor Brent challenges a common misconception in the church: that youth leadership is a lesser role. \n\nJoin us as we hear from Evan, a passionate young pastor, who shares his journey of faith and how the next generation is crucial to the future of the church. Evan reminds us that most people make a decision to follow Jesus before they turn 14, highlighting the importance of nurturing young believers. \n\nDon't miss this powerful sermon that encourages everyone, young and old, to stay spiritually awake and expectant for God's new work in their lives.",
      "thumbnails": {
        "default": {
          "url": "https://i.ytimg.com/vi/GpXf31dtaTI/default.jpg",
          "width": 120,
          "height": 90
        },
        "medium": {
          "url": "https://i.ytimg.com/vi/GpXf31dtaTI/mqdefault.jpg",
          "width": 320,
          "height": 180
        },
        "high": {
          "url": "https://i.ytimg.com/vi/GpXf31dtaTI/hqdefault.jpg",
          "width": 480,
          "height": 360
        },
        "standard": {
          "url": "https://i.ytimg.com/vi/GpXf31dtaTI/sddefault.jpg",
          "width": 640,
          "height": 480
        },
        "maxres": {
          "url": "https://i.ytimg.com/vi/GpXf31dtaTI/maxresdefault.jpg",
          "width": 1280,
          "height": 720
        }
      },
      "channelTitle": "The Church at Woodforest",
      "playlistId": "PLMRzv2jOxhfRjMMNKV3sAgPSL0f_fvpFx",
      "position": 37,
      "resourceId": {
        "kind": "youtube#video",
        "videoId": "GpXf31dtaTI"
      },
      "videoOwnerChannelTitle": "The Church at Woodforest",
      "videoOwnerChannelId": "UCP7ezytRb2i4njgDxhwHFTg"
    },
    "playlistName": "Guest speaker"
  },
  {
    "kind": "youtube#playlistItem",
    "etag": "VaSMo6CSrRCCKKmSezeShJvl4gw",
    "id": "UExNUnp2MmpPeGhmUUxyc3JGZnJ4WVdKM2NuRU5nNjdHNi41RjNCNjdGQUYwMEEyRkMx",
    "snippet": {
      "publishedAt": "2024-08-28T20:46:25Z",
      "channelId": "UCP7ezytRb2i4njgDxhwHFTg",
      "title": "Minute Message | August 29, 2024",
      "description": "",
      "thumbnails": {
        "default": {
          "url": "https://i.ytimg.com/vi/RMRqW-1VoyI/default.jpg",
          "width": 120,
          "height": 90
        },
        "medium": {
          "url": "https://i.ytimg.com/vi/RMRqW-1VoyI/mqdefault.jpg",
          "width": 320,
          "height": 180
        },
        "high": {
          "url": "https://i.ytimg.com/vi/RMRqW-1VoyI/hqdefault.jpg",
          "width": 480,
          "height": 360
        },
        "standard": {
          "url": "https://i.ytimg.com/vi/RMRqW-1VoyI/sddefault.jpg",
          "width": 640,
          "height": 480
        },
        "maxres": {
          "url": "https://i.ytimg.com/vi/RMRqW-1VoyI/maxresdefault.jpg",
          "width": 1280,
          "height": 720
        }
      },
      "channelTitle": "The Church at Woodforest",
      "playlistId": "PLMRzv2jOxhfQLrsrFfrxYWJ3cnENg67G6",
      "position": 0,
      "resourceId": {
        "kind": "youtube#video",
        "videoId": "RMRqW-1VoyI"
      },
      "videoOwnerChannelTitle": "The Church at Woodforest",
      "videoOwnerChannelId": "UCP7ezytRb2i4njgDxhwHFTg"
    },
    "playlistName": "Mid-Week Message"
  },
  {
    "kind": "youtube#playlistItem",
    "etag": "Zjb1XZNzWcm_aEvWiHlOUrtMLNY",
    "id": "UExNUnp2MmpPeGhmUUxyc3JGZnJ4WVdKM2NuRU5nNjdHNi5GRjZBMzg1QjYxMDdEQTZF",
    "snippet": {
      "publishedAt": "2024-09-04T19:37:47Z",
      "channelId": "UCP7ezytRb2i4njgDxhwHFTg",
      "title": "Minute Message | September 5, 2024",
      "description": "",
      "thumbnails": {
        "default": {
          "url": "https://i.ytimg.com/vi/xcbqZdldE3M/default.jpg",
          "width": 120,
          "height": 90
        },
        "medium": {
          "url": "https://i.ytimg.com/vi/xcbqZdldE3M/mqdefault.jpg",
          "width": 320,
          "height": 180
        },
        "high": {
          "url": "https://i.ytimg.com/vi/xcbqZdldE3M/hqdefault.jpg",
          "width": 480,
          "height": 360
        },
        "standard": {
          "url": "https://i.ytimg.com/vi/xcbqZdldE3M/sddefault.jpg",
          "width": 640,
          "height": 480
        }
      },
      "channelTitle": "The Church at Woodforest",
      "playlistId": "PLMRzv2jOxhfQLrsrFfrxYWJ3cnENg67G6",
      "position": 371,
      "resourceId": {
        "kind": "youtube#video",
        "videoId": "xcbqZdldE3M"
      },
      "videoOwnerChannelTitle": "The Church at Woodforest",
      "videoOwnerChannelId": "UCP7ezytRb2i4njgDxhwHFTg"
    },
    "playlistName": "Mid-Week Message"
  }
]